light_cache/JSONSerializer.py
light_cache/__init__.py
light_cache/cache_store.py
light_cache-0.2.1.dist-info/LICENSE
light_cache-0.2.1.dist-info/METADATA
light_cache-0.2.1.dist-info/WHEEL
light_cache-0.2.1.dist-info/RECORD
