Metadata-Version: 2.3
Name: light-cache
Version: 0.2.1
Summary: A simple, lightweight caching library for disk-based or object-based caching
License: MIT
Keywords: cache
Author: Frank Corso
Author-email: frank@frankcorso.me
Requires-Python: >=3.10
Classifier: License :: OSI Approved :: MIT License
Classifier: Programming Language :: Python :: 3
Classifier: Programming Language :: Python :: 3.10
Classifier: Programming Language :: Python :: 3.11
Classifier: Programming Language :: Python :: 3.12
Classifier: Programming Language :: Python :: 3.13
Project-URL: Repository, https://github.com/fpcorso/light-cache
